{"responseHeader":{"status":0,"QTime":11},"solr-mbeans":["CORE",{"Searcher@397a49c4[gettingstarted] main":{"class":"org.apache.solr.search.SolrIndexSearcher","version":"1.0","description":"index searcher","src":null,"stats":{"searcherName":"Searcher@397a49c4[gettingstarted] main","caching":true,"numDocs":0,"maxDoc":0,"deletedDocs":0,"reader":"ExitableDirectoryReader(UninvertingDirectoryReader())","readerDir":"org.apache.lucene.store.NRTCachingDirectory:NRTCachingDirectory(MMapDirectory@/opt/solr/server/solr/gettingstarted/data/index lockFactory=org.apache.lucene.store.NativeFSLockFactory@411bce95; maxCacheMB=48.0 maxMergeSizeMB=4.0)","indexVersion":2,"openedAt":"2018-04-17T08:40:16.974Z","registeredAt":"2018-04-17T08:40:17.061Z","warmupTime":0}},"searcher":{"class":"org.apache.solr.search.SolrIndexSearcher","version":"1.0","description":"index searcher","src":null,"stats":{"searcherName":"Searcher@397a49c4[gettingstarted] main","caching":true,"numDocs":0,"maxDoc":0,"deletedDocs":0,"reader":"ExitableDirectoryReader(UninvertingDirectoryReader())","readerDir":"org.apache.lucene.store.NRTCachingDirectory:NRTCachingDirectory(MMapDirectory@/opt/solr/server/solr/gettingstarted/data/index lockFactory=org.apache.lucene.store.NativeFSLockFactory@411bce95; maxCacheMB=48.0 maxMergeSizeMB=4.0)","indexVersion":2,"openedAt":"2018-04-17T08:40:16.974Z","registeredAt":"2018-04-17T08:40:17.061Z","warmupTime":0}},"core":{"class":"gettingstarted","version":"1.0","description":"SolrCore","src":null,"stats":{"coreName":"gettingstarted","startTime":"2018-04-17T08:40:16.419Z","refCount":2,"instanceDir":"/opt/solr/server/solr/gettingstarted","indexDir":"/opt/solr/server/solr/gettingstarted/data/index/","aliases":["gettingstarted"]}}},"QUERYHANDLER",{"/browse":{"class":"org.apache.solr.handler.component.SearchHandler","version":"5.4.1","description":"Search using components: ","src":null,"stats":{"handlerStart":1523954416910,"requests":0,"errors":0,"timeouts":0,"totalTime":0.0,"avgRequestsPerSecond":0.0,"5minRateReqsPerSecond":0.0,"15minRateReqsPerSecond":0.0,"avgTimePerRequest":0.0,"medianRequestTime":0.0,"75thPcRequestTime":0.0,"95thPcRequestTime":0.0,"99thPcRequestTime":0.0,"999thPcRequestTime":0.0}},"/admin/luke":{"class":"org.apache.solr.handler.admin.LukeRequestHandler","version":"5.4.1","description":"Lucene Index Browser.  Inspired and modeled after Luke: http://www.getopt.org/luke/","src":null,"docs":["http://wiki.apache.org/solr/LukeRequestHandler"],"stats":{"handlerStart":1523954416900,"requests":0,"errors":0,"timeouts":0,"totalTime":0.0,"avgRequestsPerSecond":0.0,"5minRateReqsPerSecond":0.0,"15minRateReqsPerSecond":0.0,"avgTimePerRequest":0.0,"medianRequestTime":0.0,"75thPcRequestTime":0.0,"95thPcRequestTime":0.0,"99thPcRequestTime":0.0,"999thPcRequestTime":0.0}},"/update/json":{"class":"org.apache.solr.handler.UpdateRequestHandler","version":"5.4.1","description":"Add documents using XML (with XSLT), CSV, JSON, or javabin","src":null,"stats":{"handlerStart":1523954416883,"requests":0,"errors":0,"timeouts":0,"totalTime":0.0,"avgRequestsPerSecond":0.0,"5minRateReqsPerSecond":0.0,"15minRateReqsPerSecond":0.0,"avgTimePerRequest":0.0,"medianRequestTime":0.0,"75thPcRequestTime":0.0,"95thPcRequestTime":0.0,"99thPcRequestTime":0.0,"999thPcRequestTime":0.0}},"/select":{"class":"org.apache.solr.handler.component.SearchHandler","version":"5.4.1","description":"Search using components: ","src":null,"stats":{"handlerStart":1523954416909,"requests":0,"errors":0,"timeouts":0,"totalTime":0.0,"avgRequestsPerSecond":0.0,"5minRateReqsPerSecond":0.0,"15minRateReqsPerSecond":0.0,"avgTimePerRequest":0.0,"medianRequestTime":0.0,"75thPcRequestTime":0.0,"95thPcRequestTime":0.0,"99thPcRequestTime":0.0,"999thPcRequestTime":0.0}},"/admin/segments":{"class":"org.apache.solr.handler.admin.SegmentsInfoRequestHandler","version":"5.4.1","description":"Lucene segments info.","src":null,"stats":{"handlerStart":1523954416906,"requests":0,"errors":0,"timeouts":0,"totalTime":0.0,"avgRequestsPerSecond":0.0,"5minRateReqsPerSecond":0.0,"15minRateReqsPerSecond":0.0,"avgTimePerRequest":0.0,"medianRequestTime":0.0,"75thPcRequestTime":0.0,"95thPcRequestTime":0.0,"99thPcRequestTime":0.0,"999thPcRequestTime":0.0}},"/admin/system":{"class":"org.apache.solr.handler.admin.SystemInfoHandler","version":"5.4.1","description":"Get System Info","src":null,"stats":{"handlerStart":1523954416900,"requests":0,"errors":0,"timeouts":0,"totalTime":0.0,"avgRequestsPerSecond":0.0,"5minRateReqsPerSecond":0.0,"15minRateReqsPerSecond":0.0,"avgTimePerRequest":0.0,"medianRequestTime":0.0,"75thPcRequestTime":0.0,"95thPcRequestTime":0.0,"99thPcRequestTime":0.0,"999thPcRequestTime":0.0}},"/schema":{"class":"org.apache.solr.handler.SchemaHandler","version":"5.4.1","description":"CRUD operations over the Solr schema","src":null,"stats":{"handlerStart":1523954416891,"requests":0,"errors":0,"timeouts":0,"totalTime":0.0,"avgRequestsPerSecond":0.0,"5minRateReqsPerSecond":0.0,"15minRateReqsPerSecond":0.0,"avgTimePerRequest":0.0,"medianRequestTime":0.0,"75thPcRequestTime":0.0,"95thPcRequestTime":0.0,"99thPcRequestTime":0.0,"999thPcRequestTime":0.0}},"/admin/plugins":{"class":"org.apache.solr.handler.admin.PluginInfoHandler","version":"5.4.1","description":"Registry","src":null,"stats":{"handlerStart":1523954416903,"requests":0,"errors":0,"timeouts":0,"totalTime":0.0,"avgRequestsPerSecond":0.0,"5minRateReqsPerSecond":0.0,"15minRateReqsPerSecond":0.0,"avgTimePerRequest":0.0,"medianRequestTime":0.0,"75thPcRequestTime":0.0,"95thPcRequestTime":0.0,"99thPcRequestTime":0.0,"999thPcRequestTime":0.0}},"/admin/logging":{"class":"org.apache.solr.handler.admin.LoggingHandler","version":"5.4.1","description":"Logging Handler","src":null,"stats":{"handlerStart":1523954416903,"requests":0,"errors":0,"timeouts":0,"totalTime":0.0,"avgRequestsPerSecond":0.0,"5minRateReqsPerSecond":0.0,"15minRateReqsPerSecond":0.0,"avgTimePerRequest":0.0,"medianRequestTime":0.0,"75thPcRequestTime":0.0,"95thPcRequestTime":0.0,"99thPcRequestTime":0.0,"999thPcRequestTime":0.0}},"/debug/dump":{"class":"org.apache.solr.handler.DumpRequestHandler","version":"5.4.1","description":"Dump handler (debug)","src":null,"stats":{"handlerStart":1523954416914,"requests":0,"errors":0,"timeouts":0,"totalTime":0.0,"avgRequestsPerSecond":0.0,"5minRateReqsPerSecond":0.0,"15minRateReqsPerSecond":0.0,"avgTimePerRequest":0.0,"medianRequestTime":0.0,"75thPcRequestTime":0.0,"95thPcRequestTime":0.0,"99thPcRequestTime":0.0,"999thPcRequestTime":0.0}},"/admin/mbeans":{"class":"org.apache.solr.handler.admin.SolrInfoMBeanHandler","version":"5.4.1","description":"Get Info (and statistics) for registered SolrInfoMBeans","src":null,"stats":{"handlerStart":1523954416902,"requests":2,"errors":0,"timeouts":0,"totalTime":25.6381,"avgRequestsPerSecond":0.2507117518601496,"5minRateReqsPerSecond":0.0,"15minRateReqsPerSecond":0.0,"avgTimePerRequest":25.6381,"medianRequestTime":25.6381,"75thPcRequestTime":25.6381,"95thPcRequestTime":25.6381,"99thPcRequestTime":25.6381,"999thPcRequestTime":25.6381}},"/update/json/docs":{"class":"org.apache.solr.handler.UpdateRequestHandler","version":"5.4.1","description":"Add documents using XML (with XSLT), CSV, JSON, or javabin","src":null,"stats":{"handlerStart":1523954416886,"requests":0,"errors":0,"timeouts":0,"totalTime":0.0,"avgRequestsPerSecond":0.0,"5minRateReqsPerSecond":0.0,"15minRateReqsPerSecond":0.0,"avgTimePerRequest":0.0,"medianRequestTime":0.0,"75thPcRequestTime":0.0,"95thPcRequestTime":0.0,"99thPcRequestTime":0.0,"999thPcRequestTime":0.0}},"/export":{"class":"org.apache.solr.handler.component.SearchHandler","version":"5.4.1","description":"Search using components: ","src":null,"stats":{"handlerStart":1523954416910,"requests":0,"errors":0,"timeouts":0,"totalTime":0.0,"avgRequestsPerSecond":0.0,"5minRateReqsPerSecond":0.0,"15minRateReqsPerSecond":0.0,"avgTimePerRequest":0.0,"medianRequestTime":0.0,"75thPcRequestTime":0.0,"95thPcRequestTime":0.0,"99thPcRequestTime":0.0,"999thPcRequestTime":0.0}},"/get":{"class":"org.apache.solr.handler.RealTimeGetHandler","version":"5.4.1","description":"The realtime get handler","src":null,"stats":{"handlerStart":1523954416897,"requests":0,"errors":0,"timeouts":0,"totalTime":0.0,"avgRequestsPerSecond":0.0,"5minRateReqsPerSecond":0.0,"15minRateReqsPerSecond":0.0,"avgTimePerRequest":0.0,"medianRequestTime":0.0,"75thPcRequestTime":0.0,"95thPcRequestTime":0.0,"99thPcRequestTime":0.0,"999thPcRequestTime":0.0}},"/admin/properties":{"class":"org.apache.solr.handler.admin.PropertiesRequestHandler","version":"5.4.1","description":"Get System Properties","src":null,"stats":{"handlerStart":1523954416903,"requests":0,"errors":0,"timeouts":0,"totalTime":0.0,"avgRequestsPerSecond":0.0,"5minRateReqsPerSecond":0.0,"15minRateReqsPerSecond":0.0,"avgTimePerRequest":0.0,"medianRequestTime":0.0,"75thPcRequestTime":0.0,"95thPcRequestTime":0.0,"99thPcRequestTime":0.0,"999thPcRequestTime":0.0}},"/admin/threads":{"class":"org.apache.solr.handler.admin.ThreadDumpHandler","version":"5.4.1","description":"Thread Dump","src":null,"stats":{"handlerStart":1523954416903,"requests":0,"errors":0,"timeouts":0,"totalTime":0.0,"avgRequestsPerSecond":0.0,"5minRateReqsPerSecond":0.0,"15minRateReqsPerSecond":0.0,"avgTimePerRequest":0.0,"medianRequestTime":0.0,"75thPcRequestTime":0.0,"95thPcRequestTime":0.0,"99thPcRequestTime":0.0,"999thPcRequestTime":0.0}},"/query":{"class":"org.apache.solr.handler.component.SearchHandler","version":"5.4.1","description":"Search using components: ","src":null,"stats":{"handlerStart":1523954416910,"requests":0,"errors":0,"timeouts":0,"totalTime":0.0,"avgRequestsPerSecond":0.0,"5minRateReqsPerSecond":0.0,"15minRateReqsPerSecond":0.0,"avgTimePerRequest":0.0,"medianRequestTime":0.0,"75thPcRequestTime":0.0,"95thPcRequestTime":0.0,"99thPcRequestTime":0.0,"999thPcRequestTime":0.0}},"/update/csv":{"class":"org.apache.solr.handler.UpdateRequestHandler","version":"5.4.1","description":"Add documents using XML (with XSLT), CSV, JSON, or javabin","src":null,"stats":{"handlerStart":1523954416884,"requests":0,"errors":0,"timeouts":0,"totalTime":0.0,"avgRequestsPerSecond":0.0,"5minRateReqsPerSecond":0.0,"15minRateReqsPerSecond":0.0,"avgTimePerRequest":0.0,"medianRequestTime":0.0,"75thPcRequestTime":0.0,"95thPcRequestTime":0.0,"99thPcRequestTime":0.0,"999thPcRequestTime":0.0}},"/replication":{"class":"org.apache.solr.handler.ReplicationHandler","version":"5.4.1","description":"ReplicationHandler provides replication of index and configuration files from Master to Slaves","src":null,"stats":{"handlerStart":1523954416895,"requests":0,"errors":0,"timeouts":0,"totalTime":0.0,"avgRequestsPerSecond":0.0,"5minRateReqsPerSecond":0.0,"15minRateReqsPerSecond":0.0,"avgTimePerRequest":0.0,"medianRequestTime":0.0,"75thPcRequestTime":0.0,"95thPcRequestTime":0.0,"99thPcRequestTime":0.0,"999thPcRequestTime":0.0,"indexSize":"71 bytes","indexVersion":0,"generation":1,"indexPath":"/opt/solr/server/solr/gettingstarted/data/index/","isMaster":"true","isSlave":"false","replicateAfter":["commit"],"replicationEnabled":"true"}},"/admin/ping":{"class":"org.apache.solr.handler.PingRequestHandler","version":"5.4.1","description":"Reports application health to a load-balancer","src":null,"stats":{"handlerStart":1523954416905,"requests":0,"errors":0,"timeouts":0,"totalTime":0.0,"avgRequestsPerSecond":0.0,"5minRateReqsPerSecond":0.0,"15minRateReqsPerSecond":0.0,"avgTimePerRequest":0.0,"medianRequestTime":0.0,"75thPcRequestTime":0.0,"95thPcRequestTime":0.0,"99thPcRequestTime":0.0,"999thPcRequestTime":0.0}},"/update":{"class":"org.apache.solr.handler.UpdateRequestHandler","version":"5.4.1","description":"Add documents using XML (with XSLT), CSV, JSON, or javabin","src":null,"stats":{"handlerStart":1523954416849,"requests":0,"errors":0,"timeouts":0,"totalTime":0.0,"avgRequestsPerSecond":0.0,"5minRateReqsPerSecond":0.0,"15minRateReqsPerSecond":0.0,"avgTimePerRequest":0.0,"medianRequestTime":0.0,"75thPcRequestTime":0.0,"95thPcRequestTime":0.0,"99thPcRequestTime":0.0,"999thPcRequestTime":0.0}},"/admin/file":{"class":"org.apache.solr.handler.admin.ShowFileRequestHandler","version":"5.4.1","description":"Admin Config File -- view or update config files directly","src":null,"stats":{"handlerStart":1523954416904,"requests":0,"errors":0,"timeouts":0,"totalTime":0.0,"avgRequestsPerSecond":0.0,"5minRateReqsPerSecond":0.0,"15minRateReqsPerSecond":0.0,"avgTimePerRequest":0.0,"medianRequestTime":0.0,"75thPcRequestTime":0.0,"95thPcRequestTime":0.0,"99thPcRequestTime":0.0,"999thPcRequestTime":0.0}},"org.apache.solr.handler.admin.CollectionsHandler":{"class":"org.apache.solr.handler.admin.CollectionsHandler","version":"5.4.1","description":"Manage SolrCloud Collections","src":null,"stats":{"handlerStart":1523954409690,"requests":0,"errors":0,"timeouts":0,"totalTime":0.0,"avgRequestsPerSecond":0.0,"5minRateReqsPerSecond":0.0,"15minRateReqsPerSecond":0.0,"avgTimePerRequest":0.0,"medianRequestTime":0.0,"75thPcRequestTime":0.0,"95thPcRequestTime":0.0,"99thPcRequestTime":0.0,"999thPcRequestTime":0.0}},"org.apache.solr.handler.admin.InfoHandler":{"class":"org.apache.solr.handler.admin.InfoHandler","version":"5.4.1","description":"System Information","src":null,"stats":{"handlerStart":1523954409692,"requests":2,"errors":0,"timeouts":0,"totalTime":79.5568,"avgRequestsPerSecond":0.17850787657972553,"5minRateReqsPerSecond":0.0066114184713530035,"15minRateReqsPerSecond":0.0022160607980413085,"avgTimePerRequest":39.7784,"medianRequestTime":39.778400000000005,"75thPcRequestTime":59.8257,"95thPcRequestTime":59.8257,"99thPcRequestTime":59.8257,"999thPcRequestTime":59.8257}},"org.apache.solr.handler.admin.CoreAdminHandler":{"class":"org.apache.solr.handler.admin.CoreAdminHandler","version":"5.4.1","description":"Manage Multiple Solr Cores","src":null,"stats":{"handlerStart":1523954409746,"requests":4,"errors":0,"timeouts":0,"totalTime":2194.6592,"avgRequestsPerSecond":0.3587431591266986,"5minRateReqsPerSecond":0.009917127707029504,"15minRateReqsPerSecond":0.0033240911970619626,"avgTimePerRequest":548.6648,"medianRequestTime":3.26645,"75thPcRequestTime":1641.564575,"95thPcRequestTime":2187.5756,"99thPcRequestTime":2187.5756,"999thPcRequestTime":2187.5756}},"org.apache.solr.handler.admin.ConfigSetsHandler":{"class":"org.apache.solr.handler.admin.ConfigSetsHandler","version":"5.4.1","description":"Manage SolrCloud ConfigSets","src":null,"stats":{"handlerStart":1523954409748,"requests":0,"errors":0,"timeouts":0,"totalTime":0.0,"avgRequestsPerSecond":0.0,"5minRateReqsPerSecond":0.0,"15minRateReqsPerSecond":0.0,"avgTimePerRequest":0.0,"medianRequestTime":0.0,"75thPcRequestTime":0.0,"95thPcRequestTime":0.0,"99thPcRequestTime":0.0,"999thPcRequestTime":0.0}}},"UPDATEHANDLER",{"updateHandler":{"class":"org.apache.solr.update.DirectUpdateHandler2","version":"1.0","description":"Update handler that efficiently directly updates the on-disk main lucene index","src":null,"stats":{"commits":0,"autocommit maxTime":"15000ms","autocommits":0,"soft autocommits":0,"optimizes":0,"rollbacks":0,"expungeDeletes":0,"docsPending":0,"adds":0,"deletesById":0,"deletesByQuery":0,"errors":0,"cumulative_adds":0,"cumulative_deletesById":0,"cumulative_deletesByQuery":0,"cumulative_errors":0,"transaction_logs_total_size":0,"transaction_logs_total_number":0}}},"CACHE",{"filterCache":{"class":"org.apache.solr.search.FastLRUCache","version":"1.0","description":"Concurrent LRU Cache(maxSize=512, initialSize=512, minSize=460, acceptableSize=486, cleanupThread=false)","src":null,"stats":{"lookups":0,"hits":0,"hitratio":0.0,"inserts":0,"evictions":0,"size":0,"warmupTime":0,"cumulative_lookups":0,"cumulative_hits":0,"cumulative_hitratio":0.0,"cumulative_inserts":0,"cumulative_evictions":0}},"perSegFilter":{"class":"org.apache.solr.search.LRUCache","version":"1.0","description":"LRU Cache(maxSize=10, initialSize=0, autowarmCount=10, regenerator=org.apache.solr.search.NoOpRegenerator@6c6c8a40)","src":null,"stats":{"lookups":0,"hits":0,"hitratio":0.0,"inserts":0,"evictions":0,"size":0,"warmupTime":0,"cumulative_lookups":0,"cumulative_hits":0,"cumulative_hitratio":0.0,"cumulative_inserts":0,"cumulative_evictions":0}},"queryResultCache":{"class":"org.apache.solr.search.LRUCache","version":"1.0","description":"LRU Cache(maxSize=512, initialSize=512)","src":null,"stats":{"lookups":0,"hits":0,"hitratio":0.0,"inserts":0,"evictions":0,"size":0,"warmupTime":0,"cumulative_lookups":0,"cumulative_hits":0,"cumulative_hitratio":0.0,"cumulative_inserts":0,"cumulative_evictions":0}},"documentCache":{"class":"org.apache.solr.search.LRUCache","version":"1.0","description":"LRU Cache(maxSize=512, initialSize=512)","src":null,"stats":{"lookups":0,"hits":0,"hitratio":0.0,"inserts":0,"evictions":0,"size":0,"warmupTime":0,"cumulative_lookups":0,"cumulative_hits":0,"cumulative_hitratio":0.0,"cumulative_inserts":0,"cumulative_evictions":0}},"fieldValueCache":{"class":"org.apache.solr.search.FastLRUCache","version":"1.0","description":"Concurrent LRU Cache(maxSize=10000, initialSize=10, minSize=9000, acceptableSize=9500, cleanupThread=false)","src":null,"stats":{"lookups":0,"hits":0,"hitratio":0.0,"inserts":0,"evictions":0,"size":0,"warmupTime":0,"cumulative_lookups":0,"cumulative_hits":0,"cumulative_hitratio":0.0,"cumulative_inserts":0,"cumulative_evictions":0}},"fieldCache":{"class":"org.apache.solr.search.SolrFieldCacheMBean","version":"1.0","description":"Provides introspection of the Solr FieldCache ","src":null,"stats":{"entries_count":0}}}]}
